odoo10_addon_sale_promotion_rule_assortment-10.0.1.0.1-py3.8-nspkg.pth
odoo/addons/sale_promotion_rule_assortment/README.rst
odoo/addons/sale_promotion_rule_assortment/__init__.py
odoo/addons/sale_promotion_rule_assortment/__manifest__.py
odoo/addons/sale_promotion_rule_assortment/demo/sale_order.xml
odoo/addons/sale_promotion_rule_assortment/demo/sale_promotion_rule.xml
odoo/addons/sale_promotion_rule_assortment/i18n/ca.po
odoo/addons/sale_promotion_rule_assortment/i18n/es.po
odoo/addons/sale_promotion_rule_assortment/i18n/sale_promotion_rule_assortment.pot
odoo/addons/sale_promotion_rule_assortment/models/__init__.py
odoo/addons/sale_promotion_rule_assortment/models/sale_promotion_rule.py
odoo/addons/sale_promotion_rule_assortment/readme/CONTRIBUTORS.rst
odoo/addons/sale_promotion_rule_assortment/readme/DESCRIPTION.rst
odoo/addons/sale_promotion_rule_assortment/readme/USAGE.rst
odoo/addons/sale_promotion_rule_assortment/static/description/icon.png
odoo/addons/sale_promotion_rule_assortment/static/description/index.html
odoo/addons/sale_promotion_rule_assortment/tests/__init__.py
odoo/addons/sale_promotion_rule_assortment/tests/test_promotion_rule_assortment.py
odoo/addons/sale_promotion_rule_assortment/views/sale_promotion_rule.xml
odoo10_addon_sale_promotion_rule_assortment-10.0.1.0.1.dist-info/METADATA
odoo10_addon_sale_promotion_rule_assortment-10.0.1.0.1.dist-info/WHEEL
odoo10_addon_sale_promotion_rule_assortment-10.0.1.0.1.dist-info/namespace_packages.txt
odoo10_addon_sale_promotion_rule_assortment-10.0.1.0.1.dist-info/top_level.txt
odoo10_addon_sale_promotion_rule_assortment-10.0.1.0.1.dist-info/RECORD
