Metadata-Version: 2.1
Name: odoo10-addon-sale-promotion-rule-assortment
Version: 10.0.1.0.1
Summary: This addon allows to reduce the appliance of a promotion rule to a set of products
Home-page: https://github.com/OCA/sale-workflow
Author: ACSONE SA/NV,Odoo Community Association (OCA)
Author-email: support@odoo-community.org
License: AGPL-3
Platform: UNKNOWN
Classifier: Programming Language :: Python
Classifier: Framework :: Odoo
Classifier: Framework :: Odoo :: 10.0
Classifier: License :: OSI Approved :: GNU Affero General Public License v3
Classifier: Development Status :: 4 - Beta
Requires-Python: ~=2.7
Requires-Dist: odoo10-addon-product-assortment
Requires-Dist: odoo10-addon-sale-promotion-rule
Requires-Dist: odoo (<10.1dev,>=10.0)
